multi_ai_handler/__init__.py
multi_ai_handler/ai_handlers.py
multi_ai_handler/extract_md.py
multi_ai_handler/generate_payload.py
multi_ai_handler/multi_ai_handler.py
multi_ai_handler-1.1.1.dist-info/METADATA
multi_ai_handler-1.1.1.dist-info/WHEEL
multi_ai_handler-1.1.1.dist-info/licenses/LICENSE
multi_ai_handler-1.1.1.dist-info/RECORD
