Metadata-Version: 2.4
Name: multi-ai-handler
Version: 1.1.1
Summary: Unified Python interface for multiple AI providers with support for text, images, and documents.
Project-URL: Homepage, https://github.com/vsharha/multi-ai-handler
Project-URL: Repository, https://github.com/vsharha/multi-ai-handler
Project-URL: Issues, https://github.com/vsharha/multi-ai-handler/issues
Author: Viktor Sharha
License: MIT
License-File: LICENSE
Keywords: ai,anthropic,api,claude,gemini,llm,openai,openrouter
Classifier: Development Status :: 3 - Alpha
Classifier: Intended Audience :: Developers
Classifier: License :: OSI Approved :: MIT License
Classifier: Programming Language :: Python :: 3
Classifier: Programming Language :: Python :: 3.11
Classifier: Programming Language :: Python :: 3.12
Classifier: Programming Language :: Python :: 3.13
Classifier: Programming Language :: Python :: 3.14
Classifier: Topic :: Scientific/Engineering :: Artificial Intelligence
Classifier: Topic :: Software Development :: Libraries :: Python Modules
Requires-Python: >=3.11
Requires-Dist: anthropic>=0.72.0
Requires-Dist: easyocr>=1.7.2
Requires-Dist: google-generativeai>=0.8.5
Requires-Dist: openai>=2.7.1
Requires-Dist: pydantic>=2.0.0
Requires-Dist: python-dotenv>=0.19.0
Provides-Extra: all
Requires-Dist: docling>=2.61.1; extra == 'all'
Requires-Dist: easyocr>=1.7.2; extra == 'all'
Requires-Dist: ollama>=0.6.0; extra == 'all'
Provides-Extra: docling
Requires-Dist: docling>=2.61.1; extra == 'docling'
Requires-Dist: easyocr>=1.7.2; extra == 'docling'
Provides-Extra: local
Requires-Dist: docling>=2.61.1; extra == 'local'
Requires-Dist: easyocr>=1.7.2; extra == 'local'
Requires-Dist: ollama>=0.6.0; extra == 'local'
Provides-Extra: ollama
Requires-Dist: ollama>=0.6.0; extra == 'ollama'
